packe/__init__.py
packe/__main__.py
packe/_cli.py
packe/_command.py
packe/_config.py
packe/_config_wrapper.py
packe/_exec/__init__.py
packe/_exec/bash_exec_prefix.py
packe/_matching/__init__.py
packe/_matching/script_selectors.py
packe/_print/__init__.py
packe/_root.py
packe/_scripts/__init__.py
packe/_scripts/indexed.py
packe/_scripts/matched_set.py
packe/_scripts/pack.py
packe/_scripts/pretty_print.py
packe/_scripts/runnable.py
packe/_scripts/script.py
packe/_scripts/types.py
packe/bash-exec/exec.bash
packe/bash-exec/utils.bash/colors.bash
packe/bash-exec/utils.bash/source-me.bash
packe/config.example.yaml
packe/main.py
packe-0.7.1.dist-info/METADATA
packe-0.7.1.dist-info/WHEEL
packe-0.7.1.dist-info/entry_points.txt
packe-0.7.1.dist-info/licenses/LICENSE.md
packe-0.7.1.dist-info/RECORD
