Metadata-Version: 2.4
Name: packe
Version: 0.7.1
Summary: Flexible bash script runner.
License: MIT
License-File: LICENSE.md
Author: GregRos
Author-email: gregros@gregros.dev
Requires-Python: >=3.9,<3.15
Classifier: License :: OSI Approved :: MIT License
Classifier: Programming Language :: Python :: 3
Classifier: Programming Language :: Python :: 3.9
Classifier: Programming Language :: Python :: 3.10
Classifier: Programming Language :: Python :: 3.11
Classifier: Programming Language :: Python :: 3.12
Classifier: Programming Language :: Python :: 3.13
Classifier: Programming Language :: Python :: 3.14
Requires-Dist: pygments (>=2.19.1,<3.0.0)
Requires-Dist: pyyaml (>=6.0.2,<7.0.0)
Requires-Dist: termcolor (>=2.5.0,<3.0.0)
Project-URL: Homepage, https://github.com/GregRos/packe
